setup.py
PerfectoLibrary/__init__.py
PerfectoLibrary/version.py
PerfectoLibrary/keywords/__init__.py
PerfectoLibrary/keywords/_devices.py
PerfectoLibrary/keywords/_general.py
PerfectoLibrary/keywords/_rest_acts.py
PerfectoLibrary/keywords/keywordgroup.py
PerfectoLibrary/listeners/__init__.py
PerfectoLibrary/listeners/_perfectoListener.py
perfectolibrary.egg-info/PKG-INFO
perfectolibrary.egg-info/SOURCES.txt
perfectolibrary.egg-info/dependency_links.txt
perfectolibrary.egg-info/requires.txt
perfectolibrary.egg-info/top_level.txt