Metadata-Version: 1.1
Name: perfectolibrary
Version: 0.4.2
Summary: Robot Framework Mobile app testing library for using Perfecto Cloud
Home-page: https://github.com/PerfectoMobileSA/Robotframework-PerfectoLibrary
Author: Jack Deng
Author-email: JackD@perfectoMobile.com
License: MIT License
Keywords: robotframework testing Perfecto mobile appium webdriver app android ios
Platform: any
Classifier: Development Status :: 3 - Alpha
Classifier: License :: OSI Approved :: MIT License
Classifier: Operating System :: OS Independent
Classifier: Programming Language :: Python
Classifier: Topic :: Software Development :: Testing
Classifier: Programming Language :: Python
Classifier: Programming Language :: Python :: 2
Classifier: Programming Language :: Python :: 2.6
Classifier: Programming Language :: Python :: 2.7
Classifier: Programming Language :: Python :: 3
Classifier: Programming Language :: Python :: 3.3
Classifier: Programming Language :: Python :: 3.4
Classifier: Programming Language :: Python :: 3.5
Classifier: Programming Language :: Python :: 3.6
